random_pass_generator/__init__.py
random_pass_generator/passgen.py
random_pass_generator-0.2.dist-info/METADATA
random_pass_generator-0.2.dist-info/WHEEL
random_pass_generator-0.2.dist-info/top_level.txt
random_pass_generator-0.2.dist-info/RECORD
