Metadata-Version: 2.1
Name: random-pass-generator
Version: 0.2
Summary: A simple library to generate random passwords.
Home-page: https://github.com/dsadasdasdsaas/random-pass-generator
Author: vsenikzianyati
Author-email: fmsg4341@gmail.com
